signal_noise_generator/__init__.py
signal_noise_generator/noise_generator/__init__.py
signal_noise_generator/noise_generator/noises.py
signal_noise_generator/signal_generator/__init__.py
signal_noise_generator/signal_generator/signals.py
signal_noise_generator-0.1.0.dist-info/METADATA
signal_noise_generator-0.1.0.dist-info/WHEEL
signal_noise_generator-0.1.0.dist-info/RECORD
