Metadata-Version: 2.1
Name: signal-noise-generator
Version: 0.1.0
Summary: 
Author: Alexandr Solodovnikov
Author-email: solodovnikov759@gmail.com
Requires-Python: >=3.11,<4.0
Classifier: Programming Language :: Python :: 3
Classifier: Programming Language :: Python :: 3.11
Classifier: Programming Language :: Python :: 3.12
Classifier: Programming Language :: Python :: 3.13
Requires-Dist: matplotlib (>=3.10.0,<4.0.0)
Requires-Dist: numpy (>=2.2.1,<3.0.0)
Requires-Dist: scipy (>=1.15.1,<2.0.0)
